trabzonspor/__init__.py
trabzonspor/cli.py
trabzonspor/scrapper.py
trabzonspor/screen.py
trabzonspor-0.7.61.dist-info/LICENSE.txt
trabzonspor-0.7.61.dist-info/METADATA
trabzonspor-0.7.61.dist-info/WHEEL
trabzonspor-0.7.61.dist-info/entry_points.txt
trabzonspor-0.7.61.dist-info/RECORD
